[{"pk": 1, "model": "mprocessor.triggerevent", "fields": {"name": "upload"}}, {"pk": 2, "model": "mprocessor.triggerevent", "fields": {"name": "sync_xmp"}}, {"pk": 1, "model": "mprocessor.pipeline", "fields": {"name": "audio_rendition", "triggers": [1], "params": "{\"ext-gen56\":{\"params\":{\"source_variant\":\"original\",\"output_variant\":\"preview\",\"output_preset\":\"MP3\",\"audio_rate\":\"44100\",\"audio_bitrate_kb\":\"128\"},\"in\":[\"ext-gen155\",\"ext-gen157\"],\"out\":[\"ext-gen153\"],\"script_name\":\"adapt_audio\",\"x\":466,\"y\":249,\"label\":\"preview\"},\"ext-gen104\":{\"params\":{\"source_variant\":\"original\"},\"in\":[],\"out\":[\"ext-gen155\"],\"script_name\":\"extract_basic\",\"x\":27,\"y\":256,\"label\":\"extract_basic\"},\"ext-gen120\":{\"params\":{\"source_variant\":\"preview\"},\"in\":[\"ext-gen153\"],\"out\":[],\"script_name\":\"extract_basic\",\"x\":917,\"y\":245,\"label\":\"extract_preview\"},\"ext-gen136\":{\"params\":{\"source_variant\":\"original\"},\"in\":[],\"out\":[\"ext-gen157\"],\"script_name\":\"extract_xmp\",\"x\":18,\"y\":413,\"label\":\"extract_xmp\"}}", "workspace": 1, "media_type": [15, 16, 17, 18, 19, 20, 21], "description": ""}}, {"pk": 2, "model": "mprocessor.pipeline", "fields": {"name": "video_rendition", "triggers": [1], "params": "{\"ext-gen56\":{\"params\":{\"source_variant\":\"original\"},\"in\":[],\"out\":[\"ext-gen282\",\"ext-gen284\"],\"script_name\":\"extract_xmp\",\"x\":15,\"y\":233,\"label\":\"extract_xmp\"},\"ext-gen72\":{\"params\":{\"source_variant\":\"original\"},\"in\":[],\"out\":[\"ext-gen286\",\"ext-gen288\"],\"script_name\":\"extract_basic\",\"x\":10,\"y\":398,\"label\":\"extract_basic\"},\"ext-gen88\":{\"params\":{\"source_variant\":\"original\",\"output_variant\":\"thumbnail\",\"frame_w\":\"100\",\"frame_h\":\"100\",\"position\":\"25\",\"output_extension\":\".jpg\"},\"in\":[\"ext-gen282\",\"ext-gen286\"],\"out\":[\"ext-gen290\"],\"script_name\":\"extract_frame\",\"x\":493,\"y\":390,\"label\":\"thumbnail\"},\"ext-gen118\":{\"params\":{\"source_variant\":\"thumbnail\"},\"in\":[\"ext-gen290\"],\"out\":[],\"script_name\":\"extract_basic\",\"x\":923,\"y\":394,\"label\":\"extract_thumbnail\"},\"ext-gen134\":{\"params\":{\"source_variant\":\"original\",\"output_variant\":\"preview\",\"output_preset\":\"FLV\",\"video_bitrate_b\":\"640000\",\"audio_bitrate_kb\":\"128\",\"video_framerate\":\"25/2\",\"audio_rate\":\"44100\",\"video_height\":\"300\",\"video_width\":\"300\"},\"in\":[\"ext-gen284\",\"ext-gen288\"],\"out\":[\"ext-gen292\"],\"script_name\":\"adapt_video\",\"x\":484,\"y\":227,\"label\":\"preview\"},\"ext-gen265\":{\"params\":{\"source_variant\":\"preview\"},\"in\":[\"ext-gen292\"],\"out\":[],\"script_name\":\"extract_basic\",\"x\":906,\"y\":222,\"label\":\"extract_preview\"}}", "workspace": 1, "media_type": [22, 23, 24, 25, 26, 27, 28, 29], "description": ""}}, {"pk": 3, "model": "mprocessor.pipeline", "fields": {"name": "image_rendition", "triggers": [1], "params": "{\"ext-gen56\":{\"params\":{\"source_variant\":\"original\",\"output_variant\":\"thumbnail\",\"resize_h\":\"100\",\"resize_w\":\"100\",\"actions\":\"resize\",\"output_extension\":\".jpg\"},\"in\":[\"ext-gen373\",\"ext-gen381\"],\"out\":[\"ext-gen371\"],\"script_name\":\"adapt_image\",\"x\":512,\"y\":234,\"label\":\"thumbnail\"},\"ext-gen134\":{\"params\":{\"source_variant\":\"thumbnail\"},\"in\":[\"ext-gen371\"],\"out\":[],\"script_name\":\"extract_basic\",\"x\":1041,\"y\":232,\"label\":\"extract_basic\"},\"ext-gen150\":{\"params\":{\"source_variant\":\"original\"},\"in\":[],\"out\":[\"ext-gen373\",\"ext-gen375\",\"ext-gen377\"],\"script_name\":\"extract_xmp\",\"x\":22,\"y\":515,\"label\":\"extract_xmp\"},\"ext-gen166\":{\"params\":{\"source_variant\":\"original\",\"output_variant\":\"fullscreen\",\"resize_h\":\"800\",\"resize_w\":\"800\",\"actions\":\"resize\",\"output_extension\":\".jpeg\"},\"in\":[\"ext-gen375\",\"ext-gen383\"],\"out\":[\"ext-gen379\"],\"script_name\":\"adapt_image\",\"x\":520,\"y\":626,\"label\":\"fullscreen\"},\"ext-gen244\":{\"params\":{\"source_variant\":\"original\"},\"in\":[],\"out\":[\"ext-gen381\",\"ext-gen383\",\"ext-gen385\"],\"script_name\":\"extract_basic\",\"x\":20,\"y\":388,\"label\":\"extract_basic\"},\"ext-gen260\":{\"params\":{\"source_variant\":\"fullscreen\"},\"in\":[\"ext-gen379\"],\"out\":[],\"script_name\":\"extract_basic\",\"x\":1043,\"y\":620,\"label\":\"extract_basic\"},\"ext-gen276\":{\"params\":{\"source_variant\":\"preview\"},\"in\":[\"ext-gen387\"],\"out\":[],\"script_name\":\"extract_basic\",\"x\":1025,\"y\":404,\"label\":\"extract_basic\"},\"ext-gen292\":{\"params\":{\"source_variant\":\"original\",\"output_variant\":\"preview\",\"resize_h\":\"300\",\"resize_w\":\"300\",\"actions\":\"resize\",\"output_extension\":\".jpeg\"},\"in\":[\"ext-gen377\",\"ext-gen385\"],\"out\":[\"ext-gen387\"],\"script_name\":\"adapt_image\",\"x\":509,\"y\":409,\"label\":\"preview\"}}", "workspace": 1, "media_type": [5, 6, 7, 8, 9, 10, 11, 12, 13, 14], "description": ""}}, {"pk": 4, "model": "mprocessor.pipeline", "fields": {"name": "doc_rendition", "triggers": [1], "params": "{\"ext-gen56\":{\"params\":{\"source_variant\":\"original\"},\"in\":[],\"out\":[\"ext-gen173\",\"ext-gen175\"],\"script_name\":\"extract_xmp\",\"x\":15,\"y\":234,\"label\":\"extract_xmp\"},\"ext-gen72\":{\"params\":{\"source_variant\":\"original\"},\"in\":[],\"out\":[\"ext-gen177\",\"ext-gen179\"],\"script_name\":\"extract_basic\",\"x\":11,\"y\":498,\"label\":\"extract_basic\"},\"ext-gen88\":{\"params\":{\"source_variant\":\"original\",\"output_variant\":\"thumbnail\",\"max_size\":\"300\",\"output_extension\":\".jpg\"},\"in\":[\"ext-gen173\",\"ext-gen177\"],\"out\":[\"ext-gen181\"],\"script_name\":\"pdfcover\",\"x\":552,\"y\":451,\"label\":\"thumbnail\"},\"ext-gen114\":{\"params\":{\"source_variant\":\"thumbnail\"},\"in\":[\"ext-gen181\"],\"out\":[],\"script_name\":\"extract_basic\",\"x\":1037,\"y\":441,\"label\":\"extract_basic\"},\"ext-gen130\":{\"params\":{\"source_variant\":\"original\",\"output_variant\":\"preview\",\"max_size\":\"300\",\"output_extension\":\".jpg\"},\"in\":[\"ext-gen175\",\"ext-gen179\"],\"out\":[\"ext-gen183\"],\"script_name\":\"pdfcover\",\"x\":561,\"y\":240,\"label\":\"preview\"},\"ext-gen156\":{\"params\":{\"source_variant\":\"preview\"},\"in\":[\"ext-gen183\"],\"out\":[],\"script_name\":\"extract_basic\",\"x\":1018,\"y\":241,\"label\":\"extract_basic\"}}", "workspace": 1, "media_type": [30], "description": ""}}, {"pk": 5, "model": "mprocessor.pipeline", "fields": {"name": "embed_xmp", "triggers": [2], "params": "{\"ext-gen57\":{\"params\":{},\"in\":[],\"out\":[],\"script_name\":\"embed_xmp\",\"x\":603,\"y\":263,\"label\":\"embed_xmp\"}}", "workspace": 1, "media_type": [5, 6, 7, 8, 9, 10, 11, 12, 13, 14, 15, 16, 17, 18, 19, 20, 21, 22, 23, 24, 25, 26, 27, 28, 29, 30], "description": ""}}]
