[{"pk": 1, "model": "scripts.script", "fields": {"pipeline": "{\"media_type\": {\"doc\": {\"source_variant\": \"original\", \"actions\": [{\"type\": \"resize\", \"parameters\": {\"max_dim\": 100}}, {\"type\": \"saveas\", \"parameters\": {\"output_format\": \"jpeg\", \"output_variant\": \"thumbnail\"}}]}, \"image\": {\"source_variant\": \"original\", \"actions\": [{\"type\": \"resize\", \"parameters\": {\"max_dim\": 100}}, {\"type\": \"saveas\", \"parameters\": {\"output_format\": \"jpeg\", \"output_variant\": \"thumbnail\"}}]}, \"video\": {\"source_variant\": \"original\", \"actions\": [{\"type\": \"extractvideothumbnail\", \"parameters\": {\"max_dim\": 100}}, {\"type\": \"saveas\", \"parameters\": {\"output_format\": \"jpeg\", \"output_variant\": \"thumbnail\"}}]}}, \"state\": \"\", \"event\": \"upload\"}", "is_global": true, "name": "thumb_generation", "state": null, "workspace": 1, "media_type": [1, 3], "description": "thumbnail generation"}}, {"pk": 2, "model": "scripts.script", "fields": {"pipeline": "{\"media_type\": {\"doc\": {\"source_variant\": \"original\", \"actions\": [{\"type\": \"resize\", \"parameters\": {\"max_dim\": 300}}, {\"type\": \"saveas\", \"parameters\": {\"output_format\": \"jpeg\", \"output_variant\": \"preview\"}}]}, \"image\": {\"source_variant\": \"original\", \"actions\": [{\"type\": \"resize\", \"parameters\": {\"max_dim\": 300}}, {\"type\": \"saveas\", \"parameters\": {\"output_format\": \"jpeg\", \"output_variant\": \"preview\"}}]}, \"audio\": {\"source_variant\": \"original\", \"actions\": [{\"type\": \"audioencode\", \"parameters\": {\"rate\": 44100, \"bitrate\": 128}}, {\"type\": \"saveas\", \"parameters\": {\"output_format\": \"mp3\", \"output_variant\": \"preview\"}}]}, \"video\": {\"source_variant\": \"original\", \"actions\": [{\"type\": \"resize\", \"parameters\": {\"width\": 300, \"height\": 300}}, {\"type\": \"videoencode\", \"parameters\": {\"bitrate\": 640, \"framerate\": \"25/2\"}}, {\"type\": \"audioencode\", \"parameters\": {\"rate\": 44100, \"bitrate\": 128}}, {\"type\": \"saveas\", \"parameters\": {\"output_format\": \"flv\", \"output_variant\": \"preview\"}}]}}, \"state\": \"\", \"event\": \"upload\"}", "is_global": true, "name": "preview_generation", "state": null, "workspace": 1, "media_type": [1, 3, 4], "description": "preview generation"}}, {"pk": 3, "model": "scripts.script", "fields": {"pipeline": "{\"media_type\": {\"image\": {\"source_variant\": \"original\", \"actions\": [{\"type\": \"resize\", \"parameters\": {\"max_dim\": 800}}, {\"type\": \"saveas\", \"parameters\": {\"output_format\": \"jpeg\", \"output_variant\": \"fullscreen\"}}]}}, \"state\": \"\", \"event\": \"upload\"}", "is_global": true, "name": "fullscreen_generation", "state": null, "workspace": 1, "media_type": [1], "description": "fullscreen generation"}}]
